<PAMDataset>
  <PAMRasterBand band="1">
    <Metadata>
      <MDI key="STATISTICS_MINIMUM">58.046825786595</MDI>
      <MDI key="STATISTICS_MAXIMUM">1063.0355458675</MDI>
      <MDI key="STATISTICS_MEAN">319.62381794885</MDI>
      <MDI key="STATISTICS_STDDEV">156.8511487816</MDI>
      <MDI key="STATISTICS_SKIPFACTORX">1</MDI>
      <MDI key="STATISTICS_SKIPFACTORY">1</MDI>
      <MDI key="STATISTICS_EXCLUDEDVALUES"></MDI>
      <MDI key="STATISTICS_COVARIANCES">24602.282874107</MDI>
    </Metadata>
  </PAMRasterBand>
</PAMDataset>
