<PAMDataset>
  <PAMRasterBand band="1">
    <Metadata>
      <MDI key="STATISTICS_MINIMUM">18.743467330747</MDI>
      <MDI key="STATISTICS_MAXIMUM">1336.8375639095</MDI>
      <MDI key="STATISTICS_MEAN">241.16262611658</MDI>
      <MDI key="STATISTICS_STDDEV">188.24140641808</MDI>
      <MDI key="STATISTICS_SKIPFACTORX">1</MDI>
      <MDI key="STATISTICS_SKIPFACTORY">1</MDI>
      <MDI key="STATISTICS_EXCLUDEDVALUES"></MDI>
      <MDI key="STATISTICS_COVARIANCES">35434.8270902572</MDI>
    </Metadata>
  </PAMRasterBand>
</PAMDataset>
