<PAMDataset>
  <PAMRasterBand band="1">
    <Metadata>
      <MDI key="STATISTICS_MINIMUM">14.992232279719</MDI>
      <MDI key="STATISTICS_MAXIMUM">625.24555926761</MDI>
      <MDI key="STATISTICS_MEAN">170.88459950859</MDI>
      <MDI key="STATISTICS_STDDEV">92.393347386223</MDI>
      <MDI key="STATISTICS_SKIPFACTORX">1</MDI>
      <MDI key="STATISTICS_SKIPFACTORY">1</MDI>
      <MDI key="STATISTICS_EXCLUDEDVALUES"></MDI>
      <MDI key="STATISTICS_COVARIANCES">8536.53064123134</MDI>
    </Metadata>
  </PAMRasterBand>
</PAMDataset>
